README.md
setup.cfg
setup.py
sunrail/__init__.py
sunrail.egg-info/PKG-INFO
sunrail.egg-info/SOURCES.txt
sunrail.egg-info/dependency_links.txt
sunrail.egg-info/top_level.txt