Metadata-Version: 1.1
Name: sunrail
Version: 1.0.3
Summary: Provides API wrapper to sunrail.com.
Home-page: https://github.com/jcconnell/python-sunrail
Author: jcconnell
Author-email: jamescarltonconnell@gmail.com
License: MIT
Platform: UNKNOWN
Classifier: License :: OSI Approved :: MIT License
Classifier: Operating System :: OS Independent
Classifier: Programming Language :: Python :: 3
